fvgp/__init__.py
fvgp/_version.py
fvgp/advanced_kernels.py
fvgp/fvgp.py
fvgp/gp.py
fvgp/gp2Scale.py
fvgp/mcmc.py
fvgp/sparse_matrix.py
fvgp-7.4.9.dist-info/AUTHORS.rst
fvgp-7.4.9.dist-info/COPYING
fvgp-7.4.9.dist-info/LICENSE
fvgp-7.4.9.dist-info/METADATA
fvgp-7.4.9.dist-info/WHEEL
fvgp-7.4.9.dist-info/entry_points.txt
fvgp-7.4.9.dist-info/top_level.txt
fvgp-7.4.9.dist-info/RECORD
