Metadata-Version: 2.1
Name: fvgp
Version: 7.4.9
Summary: Python package for highly flexible function-valued Gaussian processes (fvGP)
Home-page: https://github.com/MarcusMichaelNoack/fvgp
Author: Marcus Michael Noack
Author-email: MarcusNoack@lbl.gov
License: GNU General Public License v3
Keywords: fvgp
Classifier: Development Status :: 2 - Pre-Alpha
Classifier: Intended Audience :: Developers
Classifier: License :: OSI Approved :: GNU General Public License v3 (GPLv3)
Classifier: Natural Language :: English
Classifier: Programming Language :: Python :: 3
Classifier: Programming Language :: Python :: 3.5
Classifier: Programming Language :: Python :: 3.6
Classifier: Programming Language :: Python :: 3.7
Classifier: Programming Language :: Python :: 3.8
Requires-Python: >=3.7
License-File: LICENSE
License-File: COPYING
License-File: AUTHORS.rst
Requires-Dist: wheel
Requires-Dist: versioneer
Requires-Dist: torch (>=1.9.0)
Requires-Dist: scipy
Requires-Dist: numpy
Requires-Dist: matplotlib
Requires-Dist: dask (>=2021.6.2)
Requires-Dist: distributed (>=2021.6.2)
Requires-Dist: hgdl (==2.0.7)
Requires-Dist: notebook
Requires-Dist: plotly
Requires-Dist: loguru
Provides-Extra: docs
Requires-Dist: sphinx ; extra == 'docs'
Requires-Dist: sphinx-rtd-theme ; extra == 'docs'
Requires-Dist: myst-parser ; extra == 'docs'
Requires-Dist: myst-nb ; extra == 'docs'
Requires-Dist: sphinx-panels ; extra == 'docs'
Requires-Dist: autodocs ; extra == 'docs'
Requires-Dist: jupytext ; extra == 'docs'
Provides-Extra: tests
Requires-Dist: pytest ; extra == 'tests'
Requires-Dist: codecov ; extra == 'tests'
Requires-Dist: pytest-cov ; extra == 'tests'
